[
    {
        "fileName":"1.jpg",
        "title":"图片标题",
        "des":"在我生命中，如果有什么我无法承受失去的，那就是你。"
    },
    {
        "fileName":"2.jpg",
        "title":"图片标题",
        "des":"时间是一件很残酷的事情，随著时间渐渐过去，很多东西都会被淡化、遗忘，明明曾经是非常悲伤的往事，现在也可以拿出来像是开玩笑似的说著。这是人世间的常态，也是一件不得不如此的规矩，人们藉此忘记悲伤的过去，走向未来，如果伤痛的感觉永远强烈，就会形成一个名为“过去”的枷锁，限制住人们的脚步，永远无法步向未来，只能在原地踏步。----宁风致"
    },
    {
        "fileName":"3.jpg",
        "title":"图片标题",
        "des":"凤尾森森，龙吟细细。——曹雪芹《红楼梦》。"
    },
    {
        "fileName":"4.jpg",
        "title":"图片标题",
        "des":"不需要对生活太用力，心会带着我们去该去的地方."
    },
    {
        "fileName":"5.jpg",
        "title":"图片标题",
        "des":"我一直在等啊，等着有人知道我打字喜欢用9键还是26键；知道我吃饭喜欢用勺子还是筷子；知道我睡觉喜欢抱娃娃还是不抱娃娃；知道我难受喜欢哭还是喜欢笑；知道我喝饮料喜欢可乐还是雪碧；知道我看动漫喜欢海绵宝宝还是机器猫；知道我拍照喜欢自拍还是别人帮我拍；知道我打字喜欢用大拇指还是食指；知道我吃药喜欢喝水还是不喝水；知道我用图是喜欢小清新还是大恶搞；知道我扎马尾喜欢高马尾还是低马尾；知道我喝水喜欢喝热水还是冷水；知道我看电影喜欢看中国的还是美国的；知道城市我喜欢巴黎还是荷兰；知道我写字喜欢用黑笔还是蓝笔；知道我看小说喜欢看现代还是古代；知道我出门背包还是不背包；知道我穿鞋喜欢穿袜子还是不穿袜子；知道我啃瓜子是用左手还是右手；知道我的一切一切的小习惯"
    },
    {
        "fileName":"6.jpg",
        "title":"图片标题",
        "des":"听风与我讲你,别说离开以后还会想念，别说分手以后还是朋友，离开一个地方，那片风景就不在属于你，错过一个人，那个人便与你无关,你转身那一秒起，我的幸福便与你无关"
    },
    {
        "fileName":"7.jpg",
        "title":"图片标题",
        "des":"快意时早回首，拂心处莫放手"
    },
    {
        "fileName":"8.jpg",
        "title":"图片标题",
        "des":"爱与渴望，最最可怕"
    },
    {
        "fileName":"9.jpg",
        "title":"图片标题",
        "des":"在湖边吃饭 跑来只狗狗坐在湖边。我吃完饭狗狗还在原地。老板来结账时看着狗狗低语 又来了。我问 它是走丢了还是主人不要它了？老板说 它是流浪狗 以前还有只流浪猫。它常和野猫打架抢鱼骨头来给小猫 小猫会翻垃圾找骨头给它。后来小猫出意外死了。我问狗狗 很想它吧？狗狗说 喵。"
    },
    {
        "fileName":"10.jpg",
        "title":"图片标题",
        "des":"愿我的世界里总有你的二分之一"
    },
    {
        "fileName":"11.jpg",
        "title":"图片标题",
        "des":"爱上一个人后，你就会读懂很多歌词"
    },
    {
        "fileName":"12.jpg",
        "title":"图片标题",
        "des":"愿余生陪你到最后是那个熟悉容颜只是爱到最后成全别人我只叹无缘"
    },
    {
        "fileName":"13.jpg",
        "title":"图片标题",
        "des":"以你之姓，冠我之名。你知道它的含义吗？让我来告诉你，它背后的意思，我想嫁给你"
    },
    {
        "fileName":"14.jpg",
        "title":"图片标题",
        "des":"夕阳甚好，却已是黄昏"
    },
    {
        "fileName":"15.jpg",
        "title":"图片标题",
        "des":"或许，比起世俗的人情冷漠，有时候，孤独，也是好事"
    },
    {
        "fileName":"16.jpg",
        "title":"图片标题",
        "des":"每个傻逼身上都有一种自以为是的光芒"
    }
]
